{
  "basics": {
    "name": "Jess Jones",
    "label": "PhD candidate, Robotics & Autonomous Systems",
    "image": "",
    "email": "jess.jones@bristol.ac.uk",
    "phone": "+44 7876 116588",
    "url": "https://jessj0nes.github.io",
    "summary": "PhD candidate at the University of Bristol with a First Class BSc in Computer Science. Interested in deep learning, multi-agent reinforcement learning, and vision-based computing for robotics and trustworthy analysis of online content. Background combines research engineering with leadership in hospitality and an indoor farming start-up.",
    "location": {
      "address": "20 Brunswick Street",
      "postalCode": "BS5 9QN",
      "city": "Bristol",
      "countryCode": "GB",
      "region": "England"
    },
    "profiles": []
  },
  "work": [
    {
      "name": "CASM Technology",
      "position": "Developer & Researcher",
      "location": "",
      "startDate": "2024-02-01",
      "endDate": "",
      "summary": "Tools using foundation models and machine learning for analysis of social media, misinformation, and harmful content.",
      "highlights": [
        "Research and development on NLP and ML systems for real-world audit and safety workflows."
      ]
    },
    {
      "name": "University of Bristol — High Performance Computing Group",
      "position": "Research intern",
      "location": "Bristol, UK",
      "startDate": "2022-06-01",
      "endDate": "2022-08-31",
      "summary": "Eight-week summer internship benchmarking MGCFD-OP2 on Arm architectures.",
      "highlights": [
        "Benchmarked ThunderX2, Graviton 2, and Graviton 3.",
        "Released mgcfd-op2 and babelstream packages to the Spack repository."
      ]
    },
    {
      "name": "Motion Impossible",
      "position": "Full-stack software engineer",
      "location": "",
      "startDate": "2023-05-01",
      "endDate": "2023-09-01",
      "summary": "Architecture and UI for multi-robot camera dolly control.",
      "highlights": [
        "Designed system for simultaneous control and interaction of multiple robotic camera dollies.",
        "Implemented networking for one-to-one, one-to-many, and many-to-many device interactions."
      ]
    },
    {
      "name": "CASM Technology",
      "position": "Developer & Researcher (summers)",
      "location": "",
      "startDate": "2020-06-01",
      "endDate": "2021-09-01",
      "summary": "Summer placements supporting PhD-level NLP research and fact-checking systems.",
      "highlights": [
        "Custom entity linking in an automated fact-checking pipeline.",
        "Research contributing to a UK Cabinet Office report on technologies for operational delivery."
      ]
    },
    {
      "name": "Herb & Bloom",
      "position": "Owner & Director",
      "location": "",
      "startDate": "2017-01-01",
      "endDate": "2019-12-31",
      "summary": "Indoor vertical farming start-up operating as a PLC.",
      "highlights": [
        "Established and ran day-to-day operations and management of the business."
      ]
    },
    {
      "name": "Cubitt House",
      "position": "Operations Director",
      "location": "",
      "startDate": "2014-01-01",
      "endDate": "2017-12-31",
      "summary": "Premium pub and hotel group (~£14m turnover).",
      "highlights": [
        "Operational delivery across sites, performance, procurement, and strategic planning."
      ]
    }
  ],
  "volunteer": [],
  "education": [
    {
      "institution": "University of Bristol",
      "location": "Bristol, UK",
      "url": "https://www.bristol.ac.uk/",
      "area": "Robotics & Autonomous Systems",
      "studyType": "PhD",
      "startDate": "2023-09-01",
      "endDate": "2027-09-01",
      "score": "",
      "courses": [],
      "highlights": ["FARSCOPE Centre for Doctoral Training."]
    },
    {
      "institution": "University of Bristol",
      "location": "Bristol, UK",
      "url": "https://www.bristol.ac.uk/",
      "area": "Computer Science",
      "studyType": "BSc (First Class Honours)",
      "startDate": "2020-09-01",
      "endDate": "2023-06-01",
      "score": "",
      "courses": [],
      "highlights": [
        "Hargrave Prize for best final-year BSc thesis.",
        "NAG HPC Student Prize (second highest accreditation, HPC programme).",
        "Netcraft Prize (top ten second-year cohort)."
      ]
    }
  ],
  "awards": [
    {
      "title": "Hargrave Prize",
      "date": "2023-08-01",
      "awarder": "University of Bristol",
      "summary": "Best final-year undergraduate thesis on the BSc Computer Science programme."
    },
    {
      "title": "NAG HPC Student Prize",
      "date": "2023-07-01",
      "awarder": "University of Bristol / NAG",
      "summary": "Second highest accreditation on the High Performance Computing programme (2023)."
    },
    {
      "title": "Netcraft Prize",
      "date": "2022-07-01",
      "awarder": "University of Bristol",
      "summary": "Awarded to the top ten second-year Computer Science students (2022)."
    }
  ],
  "certificates": [],
  "publications": [
    {
      "name": "Assessing VLM-Driven Semantic Affordance Inference for Non-Humanoid Robot Morphologies",
      "publisher": "AAMAS 2026",
      "releaseDate": "2026-01-01",
      "url": "https://doi.org/10.65109/WTKR8312",
      "summary": "Evaluates vision-language models for zero-shot affordance inference on non-humanoid robots, including conservative bias with implications for safe deployment."
    }
  ],
  "skills": [
    {
      "name": "Languages",
      "level": "",
      "keywords": ["C", "C++", "C#", "Python", "Java", "Go", "Haskell", "SQL"]
    },
    {
      "name": "Tools & frameworks",
      "level": "",
      "keywords": [
        "PyTorch",
        "TensorFlow",
        "OpenMP",
        "MPI",
        "OpenCL",
        "AWS",
        "Git",
        "Unity",
        "Unreal Engine"
      ]
    }
  ],
  "languages": [],
  "interests": [],
  "references": [
    {
      "name": "Prof. Sabine Hauert",
      "reference": "PhD supervisor, University of Bristol — sabine.hauert@bristol.ac.uk"
    },
    {
      "name": "David Weir",
      "reference": "Director, CASM Technology — davidw@casmtechnology.com"
    }
  ],
  "projects": [
    {
      "name": "MARL framework for abstract communication (DOTS swarms)",
      "summary": "FARSCOPE taught component — multi-agent reinforcement learning for Bristol swarm robotics.",
      "highlights": [
        "Simulation framework for efficient MARL experiments on DOTS robots.",
        "Novel paint-mixing scenario testing communication and interpretation.",
        "Compared MARL algorithms and network architectures."
      ],
      "startDate": "2024-09-01",
      "endDate": ""
    },
    {
      "name": "3D corallite reconstruction (BSc thesis)",
      "summary": "Volumetric ViT and topological loss for segmenting coral micro-CT data (Hargrave Prize).",
      "highlights": [
        "UNet–ViT pipeline on volumetric inputs; Blender API for interactive 3D analysis."
      ],
      "startDate": "2022-09-01",
      "endDate": "2023-05-01"
    },
    {
      "name": "Lattice–Boltzmann HPC (NAG prize project)",
      "summary": "Distributed CFD mini-apps with OpenMP, MPI, and OpenCL (NAG HPC Student Prize).",
      "highlights": [
        "Architecture-specific optimisations, multi-node scaling, GPU offloading."
      ],
      "startDate": "2022-09-01",
      "endDate": "2023-05-01"
    }
  ]
}
